[
  {
    "type": "KEYWORD_TOKEN",
    "content": "sync"
  },
  {
    "type": "SYMBOL_TOKEN",
    "content": "{"
  },
  {
    "type": "NEWLINE_TOKEN",
    "content": ""
  },
  {
    "type": "KEYWORD_TOKEN",
    "content": "Piano"
  },
  {
    "type": "SYMBOL_TOKEN",
    "content": "("
  },
  {
    "type": "HAND_TOKEN",
    "content": "R"
  },
  {
    "type": "SYMBOL_TOKEN",
    "content": ","
  },
  {
    "type": "NOTE_TOKEN",
    "content": "do"
  },
  {
    "type": "SYMBOL_TOKEN",
    "content": ")"
  },
  {
    "type": "NEWLINE_TOKEN",
    "content": ""
  },
  {
    "type": "KEYWORD_TOKEN",
    "content": "Guitar"
  },
  {
    "type": "SYMBOL_TOKEN",
    "content": "("
  },
  {
    "type": "NOTE_TOKEN",
    "content": "G"
  },
  {
    "type": "SYMBOL_TOKEN",
    "content": ")"
  },
  {
    "type": "NEWLINE_TOKEN",
    "content": ""
  },
  {
    "type": "SYMBOL_TOKEN",
    "content": "}"
  },
  {
    "type": "NEWLINE_TOKEN",
    "content": ""
  },
  {
    "type": "NEWLINE_TOKEN",
    "content": ""
  }
]